odoo/addons/purchase_order_line_menu/README.rst
odoo/addons/purchase_order_line_menu/__init__.py
odoo/addons/purchase_order_line_menu/__manifest__.py
odoo/addons/purchase_order_line_menu/i18n/fr_FR.po
odoo/addons/purchase_order_line_menu/i18n/purchase_order_line_menu.pot
odoo/addons/purchase_order_line_menu/readme/CONTRIBUTORS.rst
odoo/addons/purchase_order_line_menu/readme/DESCRIPTION.rst
odoo/addons/purchase_order_line_menu/readme/USAGE.rst
odoo/addons/purchase_order_line_menu/static/description/icon.png
odoo/addons/purchase_order_line_menu/static/description/index.html
odoo/addons/purchase_order_line_menu/views/purchase_order_line_views.xml
odoo13_addon_purchase_order_line_menu-13.0.1.0.1.dev3.dist-info/METADATA
odoo13_addon_purchase_order_line_menu-13.0.1.0.1.dev3.dist-info/WHEEL
odoo13_addon_purchase_order_line_menu-13.0.1.0.1.dev3.dist-info/top_level.txt
odoo13_addon_purchase_order_line_menu-13.0.1.0.1.dev3.dist-info/RECORD
